blue_heron/__init__.py
blue_heron/board.py
blue_heron/drawing.py
blue_heron/layers.py
blue_heron/library.py
blue_heron/mocknode.py
blue_heron/root.py
blue_heron/settings.py
blue_heron/xmltools.py
blue_heron/bin/hello.py
blue_heron-0.0.0.data/scripts/hello.py
blue_heron-0.0.0.dist-info/LICENSE.md
blue_heron-0.0.0.dist-info/METADATA
blue_heron-0.0.0.dist-info/WHEEL
blue_heron-0.0.0.dist-info/top_level.txt
blue_heron-0.0.0.dist-info/RECORD
