Metadata-Version: 2.1
Name: blue_heron
Version: 0.0.0
Summary: UNKNOWN
Home-page: https://github.com/oclyke-dev/blue-heron
License: MIT
Keywords: autodesk,eagle,brd,sch,lbr
Platform: UNKNOWN
Classifier: Topic :: Utilities
License-File: LICENSE.md
